jumpstarter_driver_probe_rs/__init__.py
jumpstarter_driver_probe_rs/client.py
jumpstarter_driver_probe_rs/driver.py
jumpstarter_driver_probe_rs/driver_test.py
jumpstarter_driver_probe_rs-0.7.4.dist-info/METADATA
jumpstarter_driver_probe_rs-0.7.4.dist-info/WHEEL
jumpstarter_driver_probe_rs-0.7.4.dist-info/RECORD
