Metadata-Version: 2.4
Name: jumpstarter-driver-probe-rs
Version: 0.7.4
Summary: rust probe-rs driver for jumpstarter
Project-URL: Homepage, https://jumpstarter.dev
Project-URL: source_archive, https://github.com/jumpstarter-dev/repo/archive/c5d38de69eadbb8eb0388bcfe3430a679fff0059.zip
Author-email: Miguel Angel Ajo <miguelangel@ajo.es>
License-Expression: Apache-2.0
Requires-Python: >=3.11
Requires-Dist: anyio>=4.10.0
Requires-Dist: click>=8.1.7.2
Requires-Dist: jumpstarter-driver-opendal==0.7.4
Requires-Dist: jumpstarter==0.7.4
